wallet_finder/__init__.py
wallet_finder/core.py
wallet_finder/crypto_wallet.py
crypto_wallet_finder-1.0.10.dist-info/LICENSE
crypto_wallet_finder-1.0.10.dist-info/METADATA
crypto_wallet_finder-1.0.10.dist-info/WHEEL
crypto_wallet_finder-1.0.10.dist-info/entry_points.txt
crypto_wallet_finder-1.0.10.dist-info/top_level.txt
crypto_wallet_finder-1.0.10.dist-info/RECORD
