Metadata-Version: 2.1
Name: crypto-wallet-finder
Version: 1.0.10
Summary: A tool for finding cryptocurrency wallet seeds using parallel processing
Home-page: https://github.com/RKInnovate/wallet_finder
Author: Wallet Finder Contributors
Author-email: rbmorena42@gmail.com
Project-URL: Bug Tracker, https://github.com/RKInnovate/wallet_finder/issues
Classifier: Development Status :: 4 - Beta
Classifier: Intended Audience :: Developers
Classifier: Topic :: Software Development :: Libraries :: Python Modules
Classifier: Topic :: Security :: Cryptography
Classifier: License :: OSI Approved :: MIT License
Classifier: Programming Language :: Python :: 3
Classifier: Programming Language :: Python :: 3.6
Classifier: Programming Language :: Python :: 3.7
Classifier: Programming Language :: Python :: 3.8
Classifier: Programming Language :: Python :: 3.9
Classifier: Programming Language :: Python :: 3.10
Classifier: Operating System :: OS Independent
Requires-Python: >=3.6
License-File: LICENSE
Requires-Dist: asn1crypto==1.5.1
Requires-Dist: bip-utils==2.9.3
Requires-Dist: cbor2==5.6.5
Requires-Dist: certifi==2024.12.14
Requires-Dist: cffi==1.17.1
Requires-Dist: charset-normalizer==3.4.0
Requires-Dist: coincurve==20.0.0
Requires-Dist: crcmod==1.7
Requires-Dist: ecdsa==0.19.0
Requires-Dist: ed25519-blake2b==1.4.1
Requires-Dist: idna==3.10
Requires-Dist: more-itertools==10.5.0
Requires-Dist: py-sr25519-bindings==0.2.1
Requires-Dist: pycparser==2.22
Requires-Dist: pycryptodome==3.21.0
Requires-Dist: PyNaCl==1.5.0
Requires-Dist: requests==2.32.3
Requires-Dist: six==1.17.0
Requires-Dist: urllib3==2.3.0
